pyinf/__init__.py
pyinf/pyinf.py
pyinsertfile-1.5.dist-info/LICENSE
pyinsertfile-1.5.dist-info/METADATA
pyinsertfile-1.5.dist-info/WHEEL
pyinsertfile-1.5.dist-info/entry_points.txt
pyinsertfile-1.5.dist-info/top_level.txt
pyinsertfile-1.5.dist-info/RECORD
