Metadata-Version: 2.1
Name: pyinsertfile
Version: 1.5
Summary: Package for making main.py files
Home-page: https://github.com/Ariya1234gamer
Author: Ariya Mirzaei
Author-email: mirzaeiariya88@gmail.com
License: MIT
Keywords: Easy file
Platform: UNKNOWN
Classifier: Programming Language :: Python :: 3
Classifier: License :: OSI Approved :: MIT License
Classifier: Operating System :: OS Independent
Requires-Dist: argparse
